discord_file_database/__init__.py
discord_file_database/__main__.py
discord_file_database-1.3.0.dist-info/METADATA
discord_file_database-1.3.0.dist-info/WHEEL
discord_file_database-1.3.0.dist-info/top_level.txt
discord_file_database-1.3.0.dist-info/RECORD
