Metadata-Version: 2.1
Name: discord-file-database
Version: 1.3.0
Summary: discord database
Home-page: https://github.com/Req-kun/discord-db
Author: Req
License: MIT
Keywords: discord_embed_extensions discord_extension discord embed discord_embed
Platform: UNKNOWN
Classifier: License :: OSI Approved :: MIT License
Classifier: Programming Language :: Python :: 3.9
Requires-Dist: discord.py
Requires-Dist: bottle
